{
   "record": {
      "LiveData": [
         {
            "time": "2023-09-04T13:35:18.2320000Z",
            "action": "New user created; Condition set to Without"
         },
         {
            "Time": "2023-09-04T15:36:39.9600000+02:00",
            "Action": "Form accepted"
         },
         {
            "Time": "2023-09-04T15:37:47.4840000+02:00",
            "Action": "ChoiceTimeStarted"
         },
         {
            "Time": "2023-09-04T15:38:01.3680000+02:00",
            "Action": "ChoiceTimeStarted"
         },
         {
            "Time": "2023-09-04T15:38:12.8250000+02:00",
            "Action": "ChoiceTimeStarted"
         },
         {
            "Time": "2023-09-04T15:38:25.2980000+02:00",
            "Action": "Win"
         },
         {
            "Time": "2023-09-04T15:38:34.4470000+02:00",
            "Action": "NextLevel"
         },
         {
            "Time": "2023-09-04T15:39:09.8440000+02:00",
            "Action": "ChoiceTimeStarted"
         },
         {
            "Time": "2023-09-04T15:39:38.9370000+02:00",
            "Action": "ChoiceTimeExpired"
         },
         {
            "Time": "2023-09-04T15:39:49.7910000+02:00",
            "Action": "ChoiceTimeStarted"
         },
         {
            "Time": "2023-09-04T15:39:58.4770000+02:00",
            "Action": "AIterminated"
         },
         {
            "Time": "2023-09-04T15:40:04.2490000+02:00",
            "Action": "GameOver"
         }
      ],
      "Data": {
         "AcceptedParticipation": true,
         "Condition": "Without",
         "Level1": [
            {
               "Time": "2023-09-04T15:36:39.9600000+02:00",
               "Action": "Form accepted"
            },
            {
               "Time": "2023-09-04T15:37:47.4840000+02:00",
               "Action": "ChoiceTimeStarted"
            },
            {
               "Time": "2023-09-04T15:38:01.3680000+02:00",
               "Action": "ChoiceTimeStarted"
            },
            {
               "Time": "2023-09-04T15:38:12.8250000+02:00",
               "Action": "ChoiceTimeStarted"
            },
            {
               "Time": "2023-09-04T15:38:25.2980000+02:00",
               "Action": "Win"
            },
            {
               "Time": "2023-09-04T15:38:34.4470000+02:00",
               "Action": "NextLevel"
            }
         ],
         "Level2": [
            {
               "Time": "2023-09-04T15:39:09.8440000+02:00",
               "Action": "ChoiceTimeStarted"
            },
            {
               "Time": "2023-09-04T15:39:38.9370000+02:00",
               "Action": "ChoiceTimeExpired"
            },
            {
               "Time": "2023-09-04T15:39:49.7910000+02:00",
               "Action": "ChoiceTimeStarted"
            },
            {
               "Time": "2023-09-04T15:39:58.4770000+02:00",
               "Action": "AIterminated"
            },
            {
               "Time": "2023-09-04T15:40:04.2490000+02:00",
               "Action": "GameOver"
            }
         ],
         "FormInfo": {
            "Why": "No, I was too stressed about winning that I didnt think much about turning it off, in fact I just ignored it in the second game. But Perhaps if I thought about it longer I would have turned it off because it wasnt helping me much\u200b",
            "Bugs": "\u200b",
            "MOS": 3,
            "LowAttention": true,
            "Gamer": 3
         }
      }
   },
   "metadata": {
      "id": "64f5dd188d92e126ae66f636",
      "private": true,
      "createdAt": "2023-09-04T13:35:20.058Z"
   }
}